effective_sql
