Metadata-Version: 1.0
Name: effective-sql
Version: 0.1.20
Summary: A effective style to operate sql
Home-page: https://github.com/GitHuHao/effective_sql.git
Author: HuHao
Author-email: whohow20094702@163.com
License: GPL Licence
Keywords: pip,upsert,crud,mysql,sql
Platform: any
